riptide_plugin_php_xdebug/__init__.py
riptide_plugin_php_xdebug/plugin.py
riptide_plugin_php_xdebug-0.9.0.dist-info/LICENSE
riptide_plugin_php_xdebug-0.9.0.dist-info/METADATA
riptide_plugin_php_xdebug-0.9.0.dist-info/WHEEL
riptide_plugin_php_xdebug-0.9.0.dist-info/entry_points.txt
riptide_plugin_php_xdebug-0.9.0.dist-info/top_level.txt
riptide_plugin_php_xdebug-0.9.0.dist-info/RECORD
