Metadata-Version: 2.1
Name: riptide-plugin-php-xdebug
Version: 0.9.0
Summary: Tool to manage development environments for web applications using containers - PHP Xdebug integration
Author-email: Marco Köpcke <hello@capypara.de>
License: MIT License
Project-URL: Repository, https://github.com/theCapypara/riptide-plugin-php-xdebug
Project-URL: Documentation, https://riptide-docs.readthedocs.io
Classifier: Development Status :: 4 - Beta
Classifier: Programming Language :: Python
Classifier: Intended Audience :: Developers
Classifier: License :: OSI Approved :: MIT License
Classifier: Programming Language :: Python :: 3.8
Classifier: Programming Language :: Python :: 3.9
Classifier: Programming Language :: Python :: 3.10
Classifier: Programming Language :: Python :: 3.11
Classifier: Programming Language :: Python :: 3.12
Classifier: Programming Language :: Python :: 3.13
Requires-Python: >=3.8
License-File: LICENSE
Requires-Dist: riptide-lib <0.10,>=0.9
Requires-Dist: riptide-cli <0.10,>=0.9
Requires-Dist: Click <9.0,>=7.0
